coherence/__init__.py
coherence/analysis.py
coherence/constants.py
coherence/models.py
coherence/physical_model.py
coherence/predictions.py
coherence/visualization.py
coherence_sim-1.0.0.dist-info/METADATA
coherence_sim-1.0.0.dist-info/WHEEL
coherence_sim-1.0.0.dist-info/top_level.txt
coherence_sim-1.0.0.dist-info/RECORD
