Metadata-Version: 2.4
Name: coherence-sim
Version: 1.0.0
Summary: Библиотека для моделирования когерентности Вселенной
Author: Timur Isanov
License: MIT
Project-URL: Homepage, https://github.com/xtimon/coherence
Project-URL: Documentation, https://github.com/xtimon/coherence#readme
Project-URL: Repository, https://github.com/xtimon/coherence
Project-URL: Issues, https://github.com/xtimon/coherence/issues
Keywords: cosmology,physics,coherence,universe,simulation,holographic,fine-structure-constant
Classifier: Development Status :: 4 - Beta
Classifier: Intended Audience :: Science/Research
Classifier: License :: OSI Approved :: MIT License
Classifier: Operating System :: OS Independent
Classifier: Programming Language :: Python :: 3
Classifier: Programming Language :: Python :: 3.8
Classifier: Programming Language :: Python :: 3.9
Classifier: Programming Language :: Python :: 3.10
Classifier: Programming Language :: Python :: 3.11
Classifier: Programming Language :: Python :: 3.12
Classifier: Topic :: Scientific/Engineering :: Physics
Classifier: Topic :: Scientific/Engineering :: Astronomy
Requires-Python: >=3.8
Requires-Dist: numpy>=1.20.0
Requires-Dist: matplotlib>=3.5.0
Requires-Dist: scipy>=1.7.0
Provides-Extra: dev
Requires-Dist: pytest>=7.0.0; extra == "dev"
Requires-Dist: pytest-cov>=4.0.0; extra == "dev"
Requires-Dist: black>=23.0.0; extra == "dev"
Requires-Dist: isort>=5.12.0; extra == "dev"
Requires-Dist: mypy>=1.0.0; extra == "dev"
Provides-Extra: full
Requires-Dist: pandas>=1.3.0; extra == "full"
Requires-Dist: tqdm>=4.62.0; extra == "full"
Provides-Extra: all
Requires-Dist: coherence-sim[dev,full]; extra == "all"
Dynamic: requires-python
